[
  {
    "name": "Agkuza",
    "uniqueName": "/Lotus/Weapons/Tenno/Archwing/Melee/ArchSwordHook/ArchHookSwordWeapon",
    "secondsPerShot": 1,
    "damagePerShot": [ 52.500004, 245, 52.499992, 0, 0, 0, 0, 0, 0, 0, 0, 0, 0, 0, 0, 0, 0, 0, 0, 0 ],
    "magazineSize": 0,
    "reloadTime": 0,
    "totalDamage": 350,
    "damagePerSecond": 350,
    "trigger": "Melee",
    "description": "Tear apart incoming enemies with this massive hooked blade.",
    "accuracy": 100,
    "criticalChance": 0,
    "criticalMultiplier": 0,
    "procChance": 0,
    "fireRate": 1,
    "chargeAttack": 0,
    "spinAttack": 0,
    "leapAttack": 0,
    "wallAttack": 0,
    "slot": 0,
    "noise": "Alarming",
    "sentinel": false,
    "masteryReq": 0,
    "omegaAttenuation": 1,
    "type": "Arch-Melee",
    "archwing": true,
    "imageName": "agkuza.png",
    "category": "Archwing Melee",
    "tradable": false,
    "damage": "350.0",
    "damageTypes": {
      "impact": 52.5,
      "slash": 52.5,
      "puncture": 245
    },
    "marketCost": 150,
    "polarities": [ "Vazarin" ],
    "tags": [ "Tenno" ],
    "vaulted": false,
    "wikiaThumbnail": "https://vignette.wikia.nocookie.net/warframe/images/c/c2/ArchHookSword.png/revision/latest?cb=20160710175147",
    "wikiaUrl": "http://warframe.wikia.com/wiki/Agkuza",
    "disposition": 3
  },
  {
    "name": "Centaur",
    "uniqueName": "/Lotus/Weapons/Tenno/Archwing/Melee/Archswordandshield/ArchSwordShield",
    "secondsPerShot": 0.92307687,
    "damagePerShot": [ 28, 56, 196, 0, 0, 0, 0, 0, 0, 0, 0, 0, 0, 0, 0, 0, 0, 0, 0, 0 ],
    "magazineSize": 0,
    "reloadTime": 0,
    "totalDamage": 280,
    "damagePerSecond": 303,
    "trigger": "Melee",
    "description": "Part sword, part shield, the Centaur excels at charging headlong into enemy fire.",
    "accuracy": 100,
    "criticalChance": 0,
    "criticalMultiplier": 0,
    "procChance": 0,
    "fireRate": 1.0833334,
    "chargeAttack": 0,
    "spinAttack": 0,
    "leapAttack": 0,
    "wallAttack": 0,
    "slot": 0,
    "noise": "Alarming",
    "sentinel": false,
    "masteryReq": 0,
    "omegaAttenuation": 1,
    "type": "Arch-Melee",
    "archwing": true,
    "imageName": "centaur.png",
    "category": "Archwing Melee",
    "tradable": false,
    "damage": "280.0",
    "damageTypes": {
      "impact": 28,
      "slash": 196,
      "puncture": 56
    },
    "marketCost": 150,
    "polarities": [ "Madurai" ],
    "tags": [ "Tenno" ],
    "vaulted": false,
    "wikiaThumbnail": "https://vignette.wikia.nocookie.net/warframe/images/2/2f/Archswordandshield.png/revision/latest?cb=20141024143732",
    "wikiaUrl": "http://warframe.wikia.com/wiki/Centaur",
    "disposition": 3
  },
  {
    "name": "Kaszas",
    "uniqueName": "/Lotus/Weapons/Tenno/Archwing/Melee/ArchScythe/ArchScythe",
    "secondsPerShot": 1,
    "damagePerShot": [ 16.25, 260, 48.749992, 0, 0, 0, 0, 0, 0, 0, 0, 0, 0, 0, 0, 0, 0, 0, 0, 0 ],
    "magazineSize": 0,
    "reloadTime": 0,
    "totalDamage": 325,
    "damagePerSecond": 325,
    "trigger": "Melee",
    "description": "Become an angel of death, with this Archwing scythe.",
    "accuracy": 100,
    "criticalChance": 0,
    "criticalMultiplier": 0,
    "procChance": 0,
    "fireRate": 1,
    "chargeAttack": 0,
    "spinAttack": 0,
    "leapAttack": 0,
    "wallAttack": 0,
    "slot": 0,
    "noise": "Alarming",
    "sentinel": false,
    "masteryReq": 0,
    "omegaAttenuation": 1,
    "type": "Arch-Melee",
    "archwing": true,
    "imageName": "kaszas.png",
    "category": "Archwing Melee",
    "tradable": false,
    "damage": "325.0",
    "damageTypes": {
      "impact": 16.3,
      "slash": 48.7,
      "puncture": 260
    },
    "marketCost": 150,
    "polarities": [ "Vazarin" ],
    "tags": [ "Tenno" ],
    "vaulted": false,
    "wikiaThumbnail": "https://vignette.wikia.nocookie.net/warframe/images/2/26/ArchScythe.png/revision/latest?cb=20151002090141",
    "wikiaUrl": "http://warframe.wikia.com/wiki/Kaszas",
    "disposition": 3
  },
  {
    "name": "Knux",
    "uniqueName": "/Lotus/Weapons/Tenno/Archwing/Melee/GrnArchHand/GrnArchHandWeapon",
    "secondsPerShot": 1,
    "damagePerShot": [ 292.5, 16.25, 16.250004, 0, 0, 0, 0, 0, 0, 0, 0, 0, 0, 0, 0, 0, 0, 0, 0, 0 ],
    "magazineSize": 0,
    "reloadTime": 0,
    "totalDamage": 325,
    "damagePerSecond": 325,
    "trigger": "Melee",
    "description": "Gallium-alloy gauntlets for close-range Archwing combat. Designed by the infamous Tyl Regor.",
    "accuracy": 100,
    "criticalChance": 0,
    "criticalMultiplier": 0,
    "procChance": 0,
    "fireRate": 1,
    "chargeAttack": 0,
    "spinAttack": 0,
    "leapAttack": 0,
    "wallAttack": 0,
    "slot": 0,
    "noise": "Alarming",
    "sentinel": false,
    "masteryReq": 0,
    "omegaAttenuation": 1,
    "type": "Arch-Melee",
    "archwing": true,
    "imageName": "knux.png",
    "category": "Archwing Melee",
    "tradable": false,
    "damage": "325.0",
    "damageTypes": {
      "impact": 292.5,
      "slash": 16.25,
      "puncture": 16.25
    },
    "marketCost": 170,
    "polarities": [ "Vazarin" ],
    "tags": [ "Grineer" ],
    "vaulted": false,
    "wikiaThumbnail": "https://vignette.wikia.nocookie.net/warframe/images/4/49/GrnArchHand.png/revision/latest?cb=20150820004111",
    "wikiaUrl": "http://warframe.wikia.com/wiki/Knux",
    "disposition": 3
  },
  {
    "name": "Onorix",
    "uniqueName": "/Lotus/Weapons/Tenno/Archwing/Melee/Archaxe/ArchAxeWeapon",
    "secondsPerShot": 1,
    "damagePerShot": [ 87, 58, 145, 0, 0, 0, 0, 0, 0, 0, 0, 0, 0, 0, 0, 0, 0, 0, 0, 0 ],
    "magazineSize": 0,
    "reloadTime": 0,
    "totalDamage": 290,
    "damagePerSecond": 290,
    "trigger": "Melee",
    "description": "This laser bladed battle-axe easily hacks through a ship's defenses and the forces protecting it.",
    "accuracy": 100,
    "criticalChance": 0,
    "criticalMultiplier": 0,
    "procChance": 0,
    "fireRate": 1,
    "chargeAttack": 0,
    "spinAttack": 0,
    "leapAttack": 0,
    "wallAttack": 0,
    "slot": 0,
    "noise": "Alarming",
    "sentinel": false,
    "masteryReq": 0,
    "omegaAttenuation": 1,
    "type": "Arch-Melee",
    "archwing": true,
    "imageName": "onorix.png",
    "category": "Archwing Melee",
    "tradable": false,
    "damage": "290.0",
    "damageTypes": {
      "impact": 87,
      "slash": 145,
      "puncture": 58
    },
    "marketCost": 190,
    "polarities": [ "Madurai" ],
    "tags": [ "Tenno" ],
    "vaulted": false,
    "wikiaThumbnail": "https://vignette.wikia.nocookie.net/warframe/images/2/22/Archaxe.png/revision/latest?cb=20141028221205",
    "wikiaUrl": "http://warframe.wikia.com/wiki/Onorix",
    "disposition": 3
  },
  {
    "name": "Prisma Veritux",
    "uniqueName": "/Lotus/Weapons/Tenno/Archwing/Melee/VoidTraderArchsword/VTArchSwordWeapon",
    "secondsPerShot": 1,
    "damagePerShot": [ 45, 45, 210, 0, 0, 0, 0, 0, 0, 0, 0, 0, 0, 0, 0, 0, 0, 0, 0, 0 ],
    "magazineSize": 0,
    "reloadTime": 0,
    "totalDamage": 300,
    "damagePerSecond": 300,
    "trigger": "Melee",
    "description": "A rare object of beauty, this Archwing sword has been sheathed in prisma crystal and baptized in the Void’s energy.",
    "accuracy": 100,
    "criticalChance": 0,
    "criticalMultiplier": 0,
    "procChance": 0,
    "fireRate": 1,
    "chargeAttack": 0,
    "spinAttack": 0,
    "leapAttack": 0,
    "wallAttack": 0,
    "slot": 0,
    "noise": "Alarming",
    "sentinel": false,
    "masteryReq": 0,
    "omegaAttenuation": 1,
    "type": "Arch-Melee",
    "archwing": true,
    "imageName": "prisma-veritux.png",
    "category": "Archwing Melee",
    "tradable": false,
    "damage": "300.0",
    "damageTypes": {
      "impact": 45,
      "slash": 210,
      "puncture": 45
    },
    "polarities": [ "Vazarin" ],
    "tags": [ "Tenno", "Prisma" ],
    "vaulted": false,
    "wikiaThumbnail": "https://vignette.wikia.nocookie.net/warframe/images/e/ed/PrismaVerituxFix.png/revision/latest?cb=20150123055945",
    "wikiaUrl": "http://warframe.wikia.com/wiki/Prisma_Veritux",
    "disposition": 3
  },
  {
    "name": "Rathbone",
    "uniqueName": "/Lotus/Weapons/Tenno/Archwing/Melee/ArchHammer/ArchHammer",
    "secondsPerShot": 1.0909091,
    "damagePerShot": [ 224, 42, 13.999987, 0, 0, 0, 0, 0, 0, 0, 0, 0, 0, 0, 0, 0, 0, 0, 0, 0 ],
    "magazineSize": 0,
    "reloadTime": 0,
    "totalDamage": 280,
    "damagePerSecond": 257,
    "trigger": "Melee",
    "description": "Using Archwing’s jets for thrust, this massive hammer crushes anything in its path.",
    "accuracy": 100,
    "criticalChance": 0,
    "criticalMultiplier": 0,
    "procChance": 0,
    "fireRate": 0.91666669,
    "chargeAttack": 0,
    "spinAttack": 0,
    "leapAttack": 0,
    "wallAttack": 0,
    "slot": 0,
    "noise": "Alarming",
    "sentinel": false,
    "masteryReq": 0,
    "omegaAttenuation": 1,
    "type": "Arch-Melee",
    "archwing": true,
    "imageName": "rathbone.png",
    "category": "Archwing Melee",
    "tradable": false,
    "damage": "280.0",
    "damageTypes": {
      "impact": 224,
      "slash": 14,
      "puncture": 42
    },
    "marketCost": 160,
    "polarities": [ "Madurai" ],
    "tags": [ "Tenno" ],
    "vaulted": false,
    "wikiaThumbnail": "https://vignette.wikia.nocookie.net/warframe/images/8/8a/ArchHammer.png/revision/latest?cb=20141024143734",
    "wikiaUrl": "http://warframe.wikia.com/wiki/Rathbone",
    "disposition": 3
  },
  {
    "name": "Veritux",
    "uniqueName": "/Lotus/Weapons/Tenno/Archwing/Melee/Archsword/ArchSwordWeapon",
    "secondsPerShot": 1.1999999,
    "damagePerShot": [ 45, 45, 210, 0, 0, 0, 0, 0, 0, 0, 0, 0, 0, 0, 0, 0, 0, 0, 0, 0 ],
    "magazineSize": 0,
    "reloadTime": 0,
    "totalDamage": 300,
    "damagePerSecond": 250,
    "trigger": "Melee",
    "description": "Weightless space turns this impossibly massive sword into an agile instrument of destruction.",
    "accuracy": 100,
    "criticalChance": 0,
    "criticalMultiplier": 0,
    "procChance": 0,
    "fireRate": 0.83333337,
    "chargeAttack": 0,
    "spinAttack": 0,
    "leapAttack": 0,
    "wallAttack": 0,
    "slot": 0,
    "noise": "Alarming",
    "sentinel": false,
    "masteryReq": 0,
    "omegaAttenuation": 1,
    "type": "Arch-Melee",
    "archwing": true,
    "imageName": "veritux.png",
    "category": "Archwing Melee",
    "tradable": false,
    "damage": "300.0",
    "damageTypes": {
      "impact": 45,
      "slash": 210,
      "puncture": 45
    },
    "polarities": [ "Vazarin" ],
    "tags": [ "Tenno" ],
    "vaulted": false,
    "wikiaThumbnail": "https://vignette.wikia.nocookie.net/warframe/images/d/dc/ArchSword.png/revision/latest?cb=20141024143613",
    "wikiaUrl": "http://warframe.wikia.com/wiki/Veritux",
    "disposition": 3
  }
]